{
    "33-0": {
        "query": "SELECT *\n FROM cat_company_name_1 AS cn1,\n cat_company_name_1 AS cn2,\n cat_info_type_1 AS it1,\n cat_info_type_1 AS it2,\n cat_kind_type_1 AS kt1,\n cat_kind_type_1 AS kt2,\n cat_movie_companies_1 AS mc1,\n cat_movie_companies_1 AS mc2,\n cat_movie_info_idx_1 AS mi_idx1,\n cat_movie_info_idx_1 AS mi_idx2,\n cat_title_1 AS t1,\n cat_title_1 AS t2\n WHERE it1.id = mi_idx1.info_type_id \nAND t1.id = mi_idx1.movie_id\nAND kt1.id = t1.kind_id\nAND cn1.id = mc1.company_id\nAND t1.id = mc1.movie_id \nAND mi_idx1.movie_id = mc1.movie_id\nAND it2.id = mi_idx2.info_type_id\nAND t2.id = mi_idx2.movie_id\nAND kt2.id = t2.kind_id\nAND cn2.id = mc2.company_id\nAND t2.id = mc2.movie_id\nAND mi_idx2.movie_id = mc2.movie_id\nAND cn1.country_code = '@param0'\nAND it1.info = '@param1'\nAND it2.info = '@param2'\nAND kt1.kind IN ('@param3')\nAND kt2.kind IN ('@param4')\nAND mi_idx2.info < '@param5'\nAND t2.production_year BETWEEN @param6 AND @param7;",
        "predicates": [
            {
                "alias": "cn",
                "original_alias": "cn1",
                "column": "country_code",
                "operator": "=",
                "data_type": "text",
                "table": "cat_company_name_1",
                "join_tables": [
                    "cat_movie_companies_1"
                ],
                "join_tables_alias": [
                    "mc"
                ],
                "join_tables_column": [
                    []
                ],
                "join_conditions": [
                    "cn.id = mc.company_id"
                ],
                "left_or_right": [
                    "l"
                ]
            },
            {
                "alias": "it",
                "original_alias": "it1",
                "column": "info",
                "operator": "=",
                "data_type": "text",
                "table": "cat_info_type_1",
                "join_tables": [
                    "cat_movie_info_idx_1"
                ],
                "join_tables_alias": [
                    "mi_idx"
                ],
                "join_tables_column": [
                    []
                ],
                "join_conditions": [
                    "it.id = mi_idx.info_type_id"
                ],
                "left_or_right": [
                    "l"
                ]
            },
            {
                "alias": "it",
                "original_alias": "it2",
                "column": "info",
                "operator": "=",
                "data_type": "text",
                "table": "cat_info_type_1",
                "join_tables": [
                    "cat_movie_info_idx_1"
                ],
                "join_tables_alias": [
                    "mi_idx"
                ],
                "join_tables_column": [
                    [
                        "info"
                    ]
                ],
                "join_conditions": [
                    "it.id = mi_idx.info_type_id"
                ],
                "left_or_right": [
                    "both"
                ]
            },
            {
                "alias": "kt",
                "original_alias": "kt1",
                "column": "kind",
                "operator": "IN",
                "data_type": "text",
                "table": "cat_kind_type_1",
                "join_tables": [
                    "cat_title_1"
                ],
                "join_tables_alias": [
                    "t"
                ],
                "join_tables_column": [
                    []
                ],
                "join_conditions": [
                    "kt.id = t.kind_id"
                ],
                "left_or_right": [
                    "l"
                ]
            },
            {
                "alias": "kt",
                "original_alias": "kt2",
                "column": "kind",
                "operator": "IN",
                "data_type": "text",
                "table": "cat_kind_type_1",
                "join_tables": [
                    "cat_title_1"
                ],
                "join_tables_alias": [
                    "t"
                ],
                "join_tables_column": [
                    [
                        "production_year"
                    ]
                ],
                "join_conditions": [
                    "kt.id = t.kind_id"
                ],
                "left_or_right": [
                    "both"
                ]
            },
            {
                "alias": "mi_idx",
                "original_alias": "mi_idx2",
                "column": "info",
                "operator": "<",
                "data_type": "text",
                "table": "cat_movie_info_idx_1",
                "join_tables": [
                    "cat_info_type_1",
                    "cat_title_1",
                    "cat_movie_companies_1"
                ],
                "join_tables_alias": [
                    "it",
                    "t",
                    "mc"
                ],
                "join_tables_column": [
                    [
                        "info"
                    ],
                    [
                        "production_year"
                    ],
                    []
                ],
                "join_conditions": [
                    "it.id = mi_idx.info_type_id",
                    "t.id = mi_idx.movie_id",
                    "mi_idx.movie_id = mc.movie_id"
                ],
                "left_or_right": [
                    "both",
                    "both",
                    "l"
                ]
            },
            {
                "alias": "t",
                "original_alias": "t2",
                "column": "production_year",
                "operator": ">",
                "data_type": "int",
                "table": "cat_title_1",
                "min": 1880,
                "max": 2019,
                "join_tables": [
                    "cat_movie_info_idx_1",
                    "cat_kind_type_1",
                    "cat_movie_companies_1"
                ],
                "join_tables_alias": [
                    "mi_idx",
                    "kt",
                    "mc"
                ],
                "join_tables_column": [
                    [
                        "info"
                    ],
                    [
                        "kind"
                    ],
                    []
                ],
                "join_conditions": [
                    "t.id = mi_idx.movie_id",
                    "kt.id = t.kind_id",
                    "t.id = mc.movie_id"
                ],
                "left_or_right": [
                    "both",
                    "both",
                    "l"
                ]
            },
            {
                "alias": "t",
                "original_alias": "t2",
                "column": "production_year",
                "operator": "<",
                "data_type": "int",
                "table": "cat_title_1",
                "min": 1880,
                "max": 2019,
                "join_tables": [
                    "cat_movie_info_idx_1",
                    "cat_kind_type_1",
                    "cat_movie_companies_1"
                ],
                "join_tables_alias": [
                    "mi_idx",
                    "kt",
                    "mc"
                ],
                "join_tables_column": [
                    [
                        "info"
                    ],
                    [
                        "kind"
                    ],
                    []
                ],
                "join_conditions": [
                    "t.id = mi_idx.movie_id",
                    "kt.id = t.kind_id",
                    "t.id = mc.movie_id"
                ],
                "left_or_right": [
                    "both",
                    "both",
                    "l"
                ]
            }
        ]
    }
}