{
    "it_miidx": [
        {
            "column": "info",
            "operator": "=",
            "data_type": "text",
            "params": [
                "top 250 rank",
                "bottom 10 rank",
                "rating",
                "votes"
            ],
            "frequencies": [
                1.0,
                3.0,
                28.0,
                10.0
            ]
        }
    ],
    "ct": [
        {
            "column": "kind",
            "operator": "=",
            "data_type": "text",
            "params": [
                "production companies",
                "production companies",
                "distributors"
            ],
            "frequencies": [
                21.0,
                1.0,
                1.0
            ]
        },
        {
            "column": "kind",
            "operator": "!=",
            "data_type": "text",
            "params": [
                "production companies",
                "production companies"
            ],
            "frequencies": [
                1.0,
                1.0
            ]
        },
        {
            "column": "kind",
            "operator": "IS NOT NULL",
            "data_type": "none",
            "params": [
                NaN,
                NaN,
                NaN
            ],
            "frequencies": [
                1.0,
                1.0,
                1.0
            ]
        }
    ],
    "mc": [
        {
            "column": "note",
            "operator": "NOT LIKE",
            "data_type": "text",
            "params": [
                "%(as Metro-Goldwyn-Mayer Pictures)%",
                "%(as Metro-Goldwyn-Mayer Pictures)%",
                "%(as Metro-Goldwyn-Mayer Pictures)%",
                "%(USA)%",
                "%(USA)%",
                "%(USA)%"
            ],
            "frequencies": [
                1.0,
                2.0,
                1.0,
                1.0,
                1.0,
                1.0
            ]
        },
        {
            "column": "note",
            "operator": "LIKE",
            "data_type": "text",
            "params": [
                "%(co-production)%",
                "%(presents)%",
                "%(co-production)%",
                "%(theatrical)%",
                "%(France)%",
                "%(VHS)%",
                "%(USA)%",
                "%(Japan)%",
                "%(Japan)%",
                "%(2006)%",
                "%(2007)%",
                "%(USA)%",
                "%(worldwide)%",
                "%(Blu-ray)%",
                "%(200%)%",
                "%(worldwide)%",
                "%(200%)%"
            ],
            "frequencies": [
                1.0,
                1.0,
                1.0,
                1.0,
                1.0,
                1.0,
                1.0,
                1.0,
                1.0,
                1.0,
                1.0,
                1.0,
                1.0,
                1.0,
                1.0,
                1.0,
                1.0
            ]
        },
        {
            "column": "note",
            "operator": "IS NOT NULL",
            "data_type": "none",
            "params": [
                NaN,
                NaN
            ],
            "frequencies": [
                1.0,
                2.0
            ]
        },
        {
            "column": "note",
            "operator": "IS NULL",
            "data_type": "none",
            "params": [
                NaN
            ],
            "frequencies": [
                8.0
            ]
        }
    ]
}